drug_repurposing/__init__.py
drug_repurposing/get_data.py
drug_repurposing/rf_model.pkl
drug_repurposing_extract-0.2.3.dist-info/METADATA
drug_repurposing_extract-0.2.3.dist-info/WHEEL
drug_repurposing_extract-0.2.3.dist-info/top_level.txt
drug_repurposing_extract-0.2.3.dist-info/RECORD
