Metadata-Version: 2.1
Name: drug-repurposing-extract
Version: 0.2.3
Summary: Library for automatic generation of drug repurposing data
Author: Shiva Aryal
